oceanex_py3/__init__.py
oceanex_py3/personal.py
oceanex_py3/public.py
oceanex_py3-1.2.2.dist-info/LICENSE.txt
oceanex_py3-1.2.2.dist-info/METADATA
oceanex_py3-1.2.2.dist-info/WHEEL
oceanex_py3-1.2.2.dist-info/top_level.txt
oceanex_py3-1.2.2.dist-info/RECORD
